__init__.py
goechargerv2/__init__.py
goechargerv2/goecharger.py
goechargerv2/validations.py
goechargerv2-0.2.2.dist-info/LICENSE
goechargerv2-0.2.2.dist-info/METADATA
goechargerv2-0.2.2.dist-info/WHEEL
goechargerv2-0.2.2.dist-info/top_level.txt
goechargerv2-0.2.2.dist-info/RECORD
