Metadata-Version: 2.1
Name: goechargerv2
Version: 0.2.2
Summary: API library for the go-eCharger.
Author-email: Ingmar Mueller <ingmar.mueller@kfw.de>, Mario Macai <mario.macai@accenture.com>
Project-URL: Bug Tracker, https://github.com/openkfw/goechargerv2/issues
Project-URL: Homepage, https://github.com/openkfw/goechargerv2
Keywords: goecharger,kfw,api,cloud
Classifier: Programming Language :: Python :: 3
Classifier: License :: OSI Approved :: MIT License
Classifier: Operating System :: OS Independent
Requires-Python: >=3.7
License-File: LICENSE
Requires-Dist: requests (>=2.27.1)
Provides-Extra: dev
Requires-Dist: black ; extra == 'dev'
Requires-Dist: pylint ; extra == 'dev'
Requires-Dist: python-dotenv ; extra == 'dev'
